almanac/__init__.py
almanac/admin.py
almanac/apps.py
almanac/celery.py
almanac/conf.py
almanac/exceptions.py
almanac/fields.py
almanac/signals.py
almanac/urls.py
almanac/widgets.py
almanac/management/__init__.py
almanac/management/commands/__init__.py
almanac/management/commands/bake_all_state_data.py
almanac/management/commands/bake_statics.py
almanac/management/commands/bootstrap_almanac.py
almanac/management/commands/bootstrap_election_events.py
almanac/management/commands/bootstrap_elections.py
almanac/migrations/0001_initial.py
almanac/migrations/0002_auto_20180206_1616.py
almanac/migrations/0003_auto_20180206_2112.py
almanac/migrations/0004_auto_20180207_1839.py
almanac/migrations/0005_auto_20180209_1813.py
almanac/migrations/0006_auto_20180213_2003.py
almanac/migrations/__init__.py
almanac/models/__init__.py
almanac/models/election_event.py
almanac/serializers/__init__.py
almanac/serializers/election_event.py
almanac/tasks/__init__.py
almanac/tasks/aws.py
almanac/templatetags/__init__.py
almanac/utils/__init__.py
almanac/utils/api_auth.py
almanac/utils/auth.py
almanac/utils/aws.py
almanac/utils/importers.py
almanac/utils/signals.py
almanac/views/__init__.py
almanac/views/body.py
almanac/views/home.py
almanac/views/state.py
almanac/viewsets/__init__.py
almanac/viewsets/base.py
almanac/viewsets/election_event.py
politico_civic_almanac-0.1.0.dist-info/DESCRIPTION.rst
politico_civic_almanac-0.1.0.dist-info/METADATA
politico_civic_almanac-0.1.0.dist-info/RECORD
politico_civic_almanac-0.1.0.dist-info/WHEEL
politico_civic_almanac-0.1.0.dist-info/metadata.json
politico_civic_almanac-0.1.0.dist-info/top_level.txt
