Metadata-Version: 2.0
Name: politico-civic-almanac
Version: 0.1.0
Summary: UNKNOWN
Home-page: https://github.com/The-Politico/politico-civic-almanac
Author: POLITICO interactive news
Author-email: interactives@politico.com
License: MIT
Platform: UNKNOWN
Classifier: Development Status :: 3 - Alpha
Classifier: Framework :: Django
Classifier: Framework :: Django :: 2.0
Classifier: Intended Audience :: Developers
Classifier: Intended Audience :: Information Technology
Classifier: License :: OSI Approved :: MIT License
Classifier: Operating System :: OS Independent
Classifier: Programming Language :: Python :: 3
Classifier: Programming Language :: Python :: 3.5
Classifier: Programming Language :: Python :: 3.6
Classifier: Topic :: Internet :: WWW/HTTP
Requires-Dist: celery
Requires-Dist: dj-database-url
Requires-Dist: django
Requires-Dist: djangorestframework
Requires-Dist: politico-civic-election
Requires-Dist: politico-civic-entity
Requires-Dist: politico-civic-geography
Requires-Dist: politico-civic-government
Requires-Dist: psycopg2
Requires-Dist: pytz
Requires-Dist: redis
Provides-Extra: test
Requires-Dist: pytest; extra == 'test'
